RoboKinematics/__init__.py
RoboKinematics/src/RoboKinematics.py
RoboKinematics/src/__init__.py
RoboKinematics-1.0.2.dist-info/LICENSE
RoboKinematics-1.0.2.dist-info/METADATA
RoboKinematics-1.0.2.dist-info/WHEEL
RoboKinematics-1.0.2.dist-info/top_level.txt
RoboKinematics-1.0.2.dist-info/RECORD
