Metadata-Version: 2.1
Name: RoboKinematics
Version: 1.0.2
Summary: A Python library for robotics research and education
Home-page: https://github.com/Silas-U/RoboKinematics/tree/main
Author: Silas Udofia (Silas-U)
Author-email: silasudofia469@gmail.com
License: Apache Version 2.0
Project-URL: Bug Tracker, https://github.com/Silas-U/RoboKinematics/issues
Keywords: python,robotics,robokinematics,kinematics,trajectory-generation,jacobian,robot-manipulator
Classifier: License :: OSI Approved :: Apache Software License
Classifier: Operating System :: OS Independent
Classifier: Programming Language :: Python :: 3.7
Classifier: Programming Language :: Python :: 3.8
Classifier: Programming Language :: Python :: 3.9
Classifier: Programming Language :: Python :: 3.10
Classifier: Programming Language :: Python :: 3.11
Requires-Python: >=3.7
License-File: LICENSE
Requires-Dist: matplotlib >=3.1
Requires-Dist: numpy >=1.17.4
Requires-Dist: scipy
